{"data":{"books":{"edges":[{"node":{"data":{"Title":"The House of the Spirits","Artist":"Isabel Allende","Link":"https://www.goodreads.com/book/show/9328.The_House_of_the_Spirits"}}},{"node":{"data":{"Title":"1984","Artist":"George Orwell","Link":"https://www.goodreads.com/book/show/40961427-1984"}}},{"node":{"data":{"Title":"Into the Wild","Artist":null,"Link":"https://www.imdb.com/title/tt0758758/"}}},{"node":{"data":{"Title":"Gut: The Inside Story of Our Body's Most Underrated Organ","Artist":"Giulia Enders","Link":"https://www.goodreads.com/book/show/23013953-gut"}}},{"node":{"data":{"Title":"Steve Jobs","Artist":"Walter Isaacson","Link":"https://www.goodreads.com/book/show/11084145-steve-jobs"}}},{"node":{"data":{"Title":"The Godfather","Artist":null,"Link":"https://www.imdb.com/title/tt0068646/"}}},{"node":{"data":{"Title":"Tribe","Artist":"Sebastian Junger","Link":"https://www.goodreads.com/book/show/40940205-tribe"}}},{"node":{"data":{"Title":"Unbroken","Artist":"Laura Hillenbrand","Link":"https://www.goodreads.com/book/show/8664353-unbroken"}}},{"node":{"data":{"Title":"Sophie's World","Artist":"Jostein Gaarder","Link":"https://www.goodreads.com/book/show/10959.Sophie_s_World"}}},{"node":{"data":{"Title":"The Machine Stops","Artist":"E. M. Forster","Link":"https://www.goodreads.com/book/show/4711854-the-machine-stops"}}},{"node":{"data":{"Title":"The Catcher in the Rye","Artist":"J.D. Salinger","Link":"https://www.goodreads.com/book/show/5107.The_Catcher_in_the_Rye"}}},{"node":{"data":{"Title":"Atomic Habits","Artist":"James Clear","Link":"https://www.goodreads.com/book/show/40121378-atomic-habits"}}},{"node":{"data":{"Title":" Stories of Your Life and Others","Artist":"Ted Chiang","Link":"https://www.goodreads.com/book/show/223380.Stories_of_Your_Life_and_Others"}}},{"node":{"data":{"Title":"Stubborn Attachments","Artist":"Tyler Cowen","Link":"https://www.goodreads.com/en/book/show/31283667"}}},{"node":{"data":{"Title":"Leaders Eat Last","Artist":"Simon Sinek","Link":"https://www.goodreads.com/book/show/16144853-leaders-eat-last"}}},{"node":{"data":{"Title":"Romance of the Three Kingdoms","Artist":"Luo Guanzhong","Link":"https://www.goodreads.com/book/show/158770.Three_Kingdoms"}}},{"node":{"data":{"Title":"The Hitchhiker's Guide to the Galaxy","Artist":"Douglas Adams","Link":"https://www.goodreads.com/book/show/386162.The_Hitchhiker_s_Guide_to_the_Galaxy"}}},{"node":{"data":{"Title":"Lifespan: Why We Age—and Why We Don't Have To ","Artist":"David A. Sinclair","Link":"https://www.goodreads.com/book/show/43723901-lifespan"}}},{"node":{"data":{"Title":"Guns, Germs, and Steel","Artist":"Jared Diamond","Link":"https://www.goodreads.com/book/show/1842.Guns_Germs_and_Steel"}}},{"node":{"data":{"Title":"The Courage to Be Disliked","Artist":"Ichiro Kishimi","Link":"https://www.goodreads.com/book/show/43306206-the-courage-to-be-disliked"}}}]},"music":{"edges":[]},"films":{"edges":[{"node":{"data":{"Title":"Good Will Hunting","Artist":null,"Link":"https://www.imdb.com/title/tt0119217/"}}},{"node":{"data":{"Title":"Into the Wild","Artist":null,"Link":"https://www.imdb.com/title/tt0758758/"}}},{"node":{"data":{"Title":"The Godfather","Artist":null,"Link":"https://www.imdb.com/title/tt0068646/"}}},{"node":{"data":{"Title":"Smoke Signals","Artist":null,"Link":"https://www.imdb.com/title/tt0120321/"}}},{"node":{"data":{"Title":"Her","Artist":null,"Link":"https://www.imdb.com/title/tt1798709/"}}}]}}}